quoter/CrossEntropyLocal.py
quoter/ProcessEntropyPreprocessing.py
quoter/__init__.py
quoter/quoter_model.py
quoter/examples/ER_BA_WS_sims.py
quoter/examples/SBM_sims.py
quoter/examples/__init__.py
quoter/examples/edge_clustering.py
quoter/examples/make_SBM.py
quoter/examples/swapping_structures_analysis.py
quoter/real_networks/read_networks.py
quoter/real_networks/NETWORKS/Arxiv_ca-CondMat/Newman-Cond_mat_95-99-binary.txt
quoter/real_networks/NETWORKS/Arxiv_ca-GrQc/CA-GrQc.txt
quoter/real_networks/NETWORKS/Arxiv_ca-HepTh/hep-th.gml
quoter/real_networks/NETWORKS/Arxiv_ca-HepTh/hep-th.txt
quoter/real_networks/NETWORKS/Arxiv_ca-HepTh/hep-th_reformatted.gml
quoter/real_networks/NETWORKS/CKM_physicians/ckm.txt
quoter/real_networks/NETWORKS/Freemans_EIES/Freemans_EIES-messages_n32.txt
quoter/real_networks/NETWORKS/Freemans_EIES/Freemans_EIES-time1_n48.txt
quoter/real_networks/NETWORKS/Freemans_EIES/Freemans_EIES-time2_n48.txt
quoter/real_networks/NETWORKS/GoldenAge/HollywoodGoldenAge_about.txt
quoter/real_networks/NETWORKS/GoldenAge/HollywoodGoldenAge_matrix_1909-1919_s0.txt
quoter/real_networks/NETWORKS/GoldenAge/HollywoodGoldenAge_matrix_1909-1919_s2.txt
quoter/real_networks/NETWORKS/GoldenAge/HollywoodGoldenAge_matrix_1920-1929_s0.txt
quoter/real_networks/NETWORKS/GoldenAge/HollywoodGoldenAge_matrix_1920-1929_s2.txt
quoter/real_networks/NETWORKS/GoldenAge/HollywoodGoldenAge_matrix_1930-1939_s0.txt
quoter/real_networks/NETWORKS/GoldenAge/HollywoodGoldenAge_matrix_1930-1939_s2.txt
quoter/real_networks/NETWORKS/GoldenAge/HollywoodGoldenAge_matrix_1940-1949_s0.txt
quoter/real_networks/NETWORKS/GoldenAge/HollywoodGoldenAge_matrix_1940-1949_s2.txt
quoter/real_networks/NETWORKS/GoldenAge/HollywoodGoldenAge_matrix_1950-1959_s0.txt
quoter/real_networks/NETWORKS/GoldenAge/HollywoodGoldenAge_matrix_1950-1959_s2.txt
quoter/real_networks/NETWORKS/GoldenAge/HollywoodGoldenAge_matrix_1960-1969_s0.txt
quoter/real_networks/NETWORKS/GoldenAge/HollywoodGoldenAge_matrix_1960-1969_s2.txt
quoter_model-1.3.2.dist-info/LICENSE
quoter_model-1.3.2.dist-info/METADATA
quoter_model-1.3.2.dist-info/WHEEL
quoter_model-1.3.2.dist-info/top_level.txt
quoter_model-1.3.2.dist-info/RECORD
