Metadata-Version: 2.1
Name: quoter-model
Version: 1.3.2
Summary: A package for simulating the quoter model of information flow on networks
Author-email: jsm8989 <jsm89@cantab.ac.uk>
Project-URL: Homepage, https://github.com/jsm8989/quoter
Project-URL: Bug Tracker, https://github.com/jsm8989/quoter/issues
Classifier: Programming Language :: Python :: 3
Classifier: License :: OSI Approved :: MIT License
Classifier: Operating System :: OS Independent
Requires-Python: >=3.7
License-File: LICENSE
Requires-Dist: networkx ==3.1
Requires-Dist: numba ==0.57.0
Requires-Dist: numpy ==1.24.3
Requires-Dist: matplotlib ==3.7.1
Requires-Dist: pandas ==1.5.3
Requires-Dist: python-louvain ==0.16
Requires-Dist: nltk ==3.8.1
